sinapsis_openai/__init__.py
sinapsis_openai/helpers/__init__.py
sinapsis_openai/helpers/openai_env_var_keys.py
sinapsis_openai/helpers/openai_keys.py
sinapsis_openai/helpers/tags.py
sinapsis_openai/templates/__init__.py
sinapsis_openai/templates/openai_audio.py
sinapsis_openai/templates/openai_base.py
sinapsis_openai/templates/openai_chat.py
sinapsis_openai/templates/openai_images.py
sinapsis_openai-0.1.9.dist-info/METADATA
sinapsis_openai-0.1.9.dist-info/WHEEL
sinapsis_openai-0.1.9.dist-info/top_level.txt
sinapsis_openai-0.1.9.dist-info/RECORD
