Metadata-Version: 2.4
Name: sinapsis-openai
Version: 0.1.9
Summary: sinapsis module to handle OpenAI modules for chat completion, image edition and creation, audio generation, among other tasks
Author-email: SinapsisAI <dev@sinapsis.tech>
Project-URL: Homepage, https://sinapsis.tech
Project-URL: Documentation, https://docs.sinapsis.tech/docs
Project-URL: Tutorials, https://docs.sinapsis.tech/tutorials
Project-URL: Repository, https://github.com/Sinapsis-AI/sinapsis-openai.git
Requires-Python: >=3.10
Requires-Dist: openai>=1.55.2
Requires-Dist: sinapsis>=0.1.1
Provides-Extra: webapp-gradio
Requires-Dist: sinapsis[webapp]>=0.2.7; extra == "webapp-gradio"
Provides-Extra: data-readers
Requires-Dist: sinapsis-data-readers>=0.1.0; extra == "data-readers"
Provides-Extra: all
Requires-Dist: sinapsis-openai[webapp-gradio]; extra == "all"
Requires-Dist: sinapsis-openai[data-readers]; extra == "all"
Provides-Extra: audio-generation
Requires-Dist: pydub>=0.25.1; extra == "audio-generation"
Requires-Dist: sinapsis-openai[encode-results]; extra == "audio-generation"
Provides-Extra: image-generation
Requires-Dist: numpy==1.26.4; extra == "image-generation"
Requires-Dist: pillow>=11.3.0; extra == "image-generation"
Requires-Dist: sinapsis-openai[encode-results]; extra == "image-generation"
Provides-Extra: encode-results
Requires-Dist: sinapsis-generic-data-tools>=0.1.8; extra == "encode-results"
